{
  "PackageData": [
    {
      "Row": [
        {
          "SchemaColumnUId": "ae0e45ca-c495-4fe7-a39d-3ab7278e1617",
          "ColumnName": "Id",
          "Value": "6452f114-bc9a-4a00-aa0a-12a7fc9e5182"
        },
        {
          "SchemaColumnUId": "736c30a7-c0ec-4fa9-b034-2552b319b633",
          "ColumnName": "Name",
          "Value": ""
        },
        {
          "SchemaColumnUId": "9e53fd7c-dde4-4502-a64c-b9e34148108b",
          "ColumnName": "Description",
          "Value": ""
        }
      ]
    },
    {
      "Row": [
        {
          "SchemaColumnUId": "ae0e45ca-c495-4fe7-a39d-3ab7278e1617",
          "ColumnName": "Id",
          "Value": "865495b1-f8ae-420d-be81-d3a38d069fdb"
        },
        {
          "SchemaColumnUId": "736c30a7-c0ec-4fa9-b034-2552b319b633",
          "ColumnName": "Name",
          "Value": ""
        },
        {
          "SchemaColumnUId": "9e53fd7c-dde4-4502-a64c-b9e34148108b",
          "ColumnName": "Description",
          "Value": ""
        }
      ]
    },
    {
      "Row": [
        {
          "SchemaColumnUId": "ae0e45ca-c495-4fe7-a39d-3ab7278e1617",
          "ColumnName": "Id",
          "Value": "d1d359fd-395e-42cb-9ebb-0f9f20c21fd2"
        },
        {
          "SchemaColumnUId": "736c30a7-c0ec-4fa9-b034-2552b319b633",
          "ColumnName": "Name",
          "Value": ""
        },
        {
          "SchemaColumnUId": "9e53fd7c-dde4-4502-a64c-b9e34148108b",
          "ColumnName": "Description",
          "Value": ""
        }
      ]
    },
    {
      "Row": [
        {
          "SchemaColumnUId": "ae0e45ca-c495-4fe7-a39d-3ab7278e1617",
          "ColumnName": "Id",
          "Value": "da24b690-08d9-4774-87e9-629ff0e95d26"
        },
        {
          "SchemaColumnUId": "736c30a7-c0ec-4fa9-b034-2552b319b633",
          "ColumnName": "Name",
          "Value": ""
        },
        {
          "SchemaColumnUId": "9e53fd7c-dde4-4502-a64c-b9e34148108b",
          "ColumnName": "Description",
          "Value": ""
        }
      ]
    }
  ]
}